README
setup.py
django_sqs/__init__.py
django_sqs/message.py
django_sqs/models.py
django_sqs/registered_queue.py
django_sqs/urls.py
django_sqs/views.py
django_sqs/management/__init__.py
django_sqs/management/commands/__init__.py
django_sqs/management/commands/runreceiver.py
django_sqs/management/commands/sqs_clear.py
django_sqs/management/commands/sqs_status.py
django_sqs/management/commands/sqs_wait.py
django_sqs_qc.egg-info/PKG-INFO
django_sqs_qc.egg-info/SOURCES.txt
django_sqs_qc.egg-info/dependency_links.txt
django_sqs_qc.egg-info/not-zip-safe
django_sqs_qc.egg-info/top_level.txt