Metadata-Version: 1.1
Name: django-sqs-qc
Version: 0.2
Summary: django package to use existing Amazon SQS Queue
Home-page: https://github.com/nauman3128/sqs-django-qc
Author: Nauman Tariq
Author-email: nauman3128@gmail.com
License: UNKNOWN
Platform: UNKNOWN
Classifier: Environment :: Web Environment
Classifier: Intended Audience :: Developers
Classifier: Operating System :: OS Independent
Classifier: Programming Language :: Python
Classifier: Framework :: Django
